[{"name":"Antofagasta Holdings","price":"753.25","change_amount":"+25.50","change_percent":"+3.51%","date":"2016-12-07T14:12:01.533Z","_id":"093495e8332c4e66ad75316e682dc934"},{"name":"Antofagasta Holdings","price":"753.75","change_amount":"+26.00","change_percent":"+3.57%","date":"2016-12-07T14:38:22.849Z","_id":"70029d8f28794265bf0c99c9f2bf7f81"},{"name":"Antofagasta Holdings","price":"742.75","change_amount":"+15.00","change_percent":"+2.06%","date":"2016-12-07T16:31:50.193Z","_id":"441550e522fd46aebd034d669475bb86"},{"name":"Antofagasta Holdings","price":"741.75","change_amount":"+14.50","change_percent":"+1.99%","date":"2016-12-07T16:35:22.678Z","_id":"f0773282a0a143ab8268b61f49c04bcf"},{"name":"Antofagasta Holdings","price":"737.50","change_amount":"+10.00","change_percent":"+1.37%","date":"2016-12-07T16:40:13.453Z","_id":"1fa7db0b375c41e29b967687706b7f92"},{"name":"Antofagasta Holdings","price":"737.25","change_amount":"+9.50","change_percent":"+1.31%","date":"2016-12-07T16:40:21.544Z","_id":"0b4a0318f3cf4b8e9242c741814471c4"},{"name":"Antofagasta Holdings","price":"738.75","change_amount":"+11.00","change_percent":"+1.51%","date":"2016-12-07T16:40:44.471Z","_id":"67d85a96cfe54c3883044621955e4861"},{"name":"Antofagasta Holdings","price":"739.00","change_amount":"+11.00","change_percent":"+1.51%","date":"2016-12-07T16:40:59.872Z","_id":"6840a33a05ac4be6a79261d36abbdf9d"},{"name":"Antofagasta Holdings","price":"739.25","change_amount":"+11.50","change_percent":"+1.58%","date":"2016-12-07T16:41:15.292Z","_id":"e81305c7a50d40bba42c8e9317350afe"},{"name":"Antofagasta Holdings","price":"739.25","change_amount":"+11.50","change_percent":"+1.58%","date":"2016-12-07T16:41:40.816Z","_id":"0d5f7224b1b84445abd4143165bc83bb"},{"name":"Antofagasta Holdings","price":"737.25","change_amount":"+9.50","change_percent":"+1.31%","date":"2016-12-07T16:44:30.731Z","_id":"dd9b7d95317842d787ab858a7d77a754"},{"name":"Antofagasta Holdings","price":"738.50","change_amount":"+11.50","change_percent":"+1.58%","date":"2016-12-07T16:44:59.032Z","_id":"d052f82898f047ea98d7b4e094e9b044"},{"name":"Antofagasta Holdings","price":"738.50","change_amount":"+11.50","change_percent":"+1.58%","date":"2016-12-07T16:46:39.084Z","_id":"cf8c3f450643436b821b8bc2b94e436a"},{"name":"Antofagasta Holdings","price":"738.50","change_amount":"+11.50","change_percent":"+1.58%","date":"2016-12-07T16:46:48.239Z","_id":"fcc6ee21d49f4aeeb6950e06cd7c88f6"},{"name":"Antofagasta Holdings","price":"738.50","change_amount":"+11.50","change_percent":"+1.58%","date":"2016-12-07T16:47:15.485Z","_id":"d139563530f74d99b0b38d53e94e8e0c"},{"name":"Antofagasta Holdings","price":"738.50","change_amount":"+11.50","change_percent":"+1.58%","date":"2016-12-07T16:48:02.006Z","_id":"6e2c95e030354a088d48b8496905094d"},{"name":"Antofagasta Holdings","price":"738.50","change_amount":"+11.50","change_percent":"+1.58%","date":"2016-12-07T16:48:08.118Z","_id":"9b39168675064110b34eb768a59d630c"},{"name":"Antofagasta Holdings","price":"738.50","change_amount":"+11.50","change_percent":"+1.58%","date":"2016-12-07T16:50:06.906Z","_id":"d9d0f8ce58834c248c97ff19e670e988"},{"name":"Antofagasta Holdings","price":"740.50","change_amount":"+13.00","change_percent":"+1.79%","date":"2016-12-07T16:54:56.156Z","_id":"9f825c9f1bc44eaeb725ffeeec71ad69"},{"name":"Antofagasta Holdings","price":"740.50","change_amount":"+13.00","change_percent":"+1.79%","date":"2016-12-07T16:57:09.405Z","_id":"0ac0795ad47c4332ae029d5df48eb089"},{"name":"Antofagasta Holdings","price":"740.50","change_amount":"+13.00","change_percent":"+1.79%","date":"2016-12-07T17:00:45.873Z","_id":"8c920ea68f5b499caf27fef5e969939b"},{"name":"Antofagasta Holdings","price":"740.50","change_amount":"+13.00","change_percent":"+1.79%","date":"2016-12-07T17:02:27.028Z","_id":"f3830345144248848b1f90facd9b4ba4"},{"name":"Antofagasta Holdings","price":"740.50","change_amount":"+13.00","change_percent":"+1.79%","date":"2016-12-07T17:05:05.166Z","_id":"c76aa29fd036410d9a03ebd610f86b26"},{"name":"Antofagasta Holdings","price":"740.50","change_amount":"+13.00","change_percent":"+1.79%","date":"2016-12-07T17:09:04.610Z","_id":"c2beaceeb964451d88802e56b1a0e1e0"},{"name":"Antofagasta Holdings","price":"740.50","change_amount":"+13.00","change_percent":"+1.79%","date":"2016-12-07T17:09:20.349Z","_id":"5cdfdb5fe59048adacecb7603b42d690"},{"name":"Antofagasta Holdings","price":"740.50","change_amount":"+13.00","change_percent":"+1.79%","date":"2016-12-07T17:09:40.249Z","_id":"57f15c5c653f4a81862442601067f239"},{"name":"Antofagasta Holdings","price":"740.50","change_amount":"+13.00","change_percent":"+1.79%","date":"2016-12-07T17:09:57.331Z","_id":"44e63683565f4d05a5d552db8f32209f"},{"name":"Antofagasta Holdings","price":"740.50","change_amount":"+13.00","change_percent":"+1.79%","date":"2016-12-07T17:10:31.700Z","_id":"5fa56511c7944a59a64c7990fc8cd415"},{"name":"Antofagasta Holdings","price":"740.50","change_amount":"+13.00","change_percent":"+1.79%","date":"2016-12-07T17:11:28.881Z","_id":"f482f9b6d30744c9b2db811cb22f5e24"},{"name":"Antofagasta Holdings","price":"740.50","change_amount":"+13.00","change_percent":"+1.79%","date":"2016-12-07T17:12:16.127Z","_id":"560ea087faba43239b083fc1cbe506cd"},{"name":"Antofagasta Holdings","price":"740.50","change_amount":"+13.00","change_percent":"+1.79%","date":"2016-12-07T17:12:29.459Z","_id":"8c1deb241f574d23b9b76fe4d537609e"},{"name":"Antofagasta Holdings","price":"740.50","change_amount":"+13.00","change_percent":"+1.79%","date":"2016-12-07T17:14:19.262Z","_id":"71d409360f8a4c7a8c805df0d116a98b"},{"name":"Antofagasta Holdings","price":"740.50","change_amount":"+13.00","change_percent":"+1.79%","date":"2016-12-07T17:16:27.921Z","_id":"6a4b0a16ede947ec95192409261b2275"},{"name":"Antofagasta Holdings","price":"740.50","change_amount":"+13.00","change_percent":"+1.79%","date":"2016-12-07T17:23:52.545Z","_id":"4ca2ac2e13894d34816013acb5d99f56"},{"name":"Antofagasta Holdings","price":"740.50","change_amount":"+13.00","change_percent":"+1.79%","date":"2016-12-07T17:25:33.219Z","_id":"8283ff9e0a8c4bcba4a875e698433e1e"},{"name":"Antofagasta Holdings","price":"740.50","change_amount":"+13.00","change_percent":"+1.79%","date":"2016-12-07T17:26:00.783Z","_id":"647a8f50862442dbb4d8625294ad4887"},{"name":"Antofagasta Holdings","price":"740.50","change_amount":"+13.00","change_percent":"+1.79%","date":"2016-12-07T17:26:28.524Z","_id":"312ab64bbe1541988740af639f6140fb"},{"name":"Antofagasta Holdings","price":"740.50","change_amount":"+13.00","change_percent":"+1.79%","date":"2016-12-07T17:26:46.219Z","_id":"2a4845113f214a7f9483e9d6d44fcff1"},{"name":"Antofagasta Holdings","price":"740.50","change_amount":"+13.00","change_percent":"+1.79%","date":"2016-12-07T17:27:25.347Z","_id":"67c74cb13fe9401493316e53c7bbfd5a"},{"name":"Antofagasta Holdings","price":"740.50","change_amount":"+13.00","change_percent":"+1.79%","date":"2016-12-07T17:27:46.003Z","_id":"21ea0f9c037541c285e10f8a77c60145"},{"name":"Antofagasta Holdings","price":"740.50","change_amount":"+13.00","change_percent":"+1.79%","date":"2016-12-07T17:28:05.692Z","_id":"af37bee6e72a4141910f093bec568a75"},{"name":"Antofagasta Holdings","price":"740.50","change_amount":"+13.00","change_percent":"+1.79%","date":"2016-12-07T17:28:28.839Z","_id":"9f6afeb6b72f42c9b7c577e375ef13d1"},{"name":"Antofagasta Holdings","price":"740.50","change_amount":"+13.00","change_percent":"+1.79%","date":"2016-12-07T17:29:11.129Z","_id":"4626745c1ae041c9a99287aa21c01b5c"},{"name":"Antofagasta Holdings","price":"740.50","change_amount":"+13.00","change_percent":"+1.79%","date":"2016-12-07T17:30:29.056Z","_id":"f707a10a7e5d44c1928be111207b5624"}]