[{"name":"Worldpay Group Plc","price":"256.70","change_amount":"-2.20","change_percent":"-0.85%","date":"2016-12-07T14:12:01.533Z","_id":"052bcd0f51b14cf38c8f133daa09d96a"},{"name":"Worldpay Group Plc","price":"256.75","change_amount":"-2.00","change_percent":"-0.77%","date":"2016-12-07T14:38:22.849Z","_id":"1b360c787946442ea68efacb073cac3a"},{"name":"Worldpay Group Plc","price":"256.75","change_amount":"-2.00","change_percent":"-0.77%","date":"2016-12-07T16:31:50.193Z","_id":"fcc60a57200d4be99a3d3205752990b7"},{"name":"Worldpay Group Plc","price":"256.85","change_amount":"-2.00","change_percent":"-0.77%","date":"2016-12-07T16:35:22.678Z","_id":"c7d6101bc99e46b595eebca73688e6a8"},{"name":"Worldpay Group Plc","price":"256.65","change_amount":"-2.10","change_percent":"-0.81%","date":"2016-12-07T16:40:13.453Z","_id":"287c8468644a4ac8b3adf53d4dbd5f2d"},{"name":"Worldpay Group Plc","price":"256.60","change_amount":"-2.20","change_percent":"-0.85%","date":"2016-12-07T16:40:21.544Z","_id":"42554a68919d4d359bdd2555740eb535"},{"name":"Worldpay Group Plc","price":"256.65","change_amount":"-2.20","change_percent":"-0.85%","date":"2016-12-07T16:40:44.471Z","_id":"7c0524ba54ec4751a5470c7e0f403844"},{"name":"Worldpay Group Plc","price":"256.65","change_amount":"-2.20","change_percent":"-0.85%","date":"2016-12-07T16:40:59.872Z","_id":"de2f8ed724d740dd9bc10f1bbb2da05b"},{"name":"Worldpay Group Plc","price":"256.65","change_amount":"-2.20","change_percent":"-0.85%","date":"2016-12-07T16:41:15.292Z","_id":"e4c89820aaef44c297a68731aaef5651"},{"name":"Worldpay Group Plc","price":"256.65","change_amount":"-2.20","change_percent":"-0.85%","date":"2016-12-07T16:41:40.816Z","_id":"8b0cc944bded48afaf1550c4ff69a0f4"},{"name":"Worldpay Group Plc","price":"256.65","change_amount":"-2.10","change_percent":"-0.81%","date":"2016-12-07T16:44:30.731Z","_id":"41e37d349e2f477c986b15737317bf77"},{"name":"Worldpay Group Plc","price":"256.50","change_amount":"-2.20","change_percent":"-0.85%","date":"2016-12-07T16:44:59.032Z","_id":"13810ebd0dba477eb4c4294abc8bec90"},{"name":"Worldpay Group Plc","price":"256.50","change_amount":"-2.20","change_percent":"-0.85%","date":"2016-12-07T16:46:39.084Z","_id":"80e71449f0644b36adcfa130ba65634d"},{"name":"Worldpay Group Plc","price":"256.50","change_amount":"-2.20","change_percent":"-0.85%","date":"2016-12-07T16:46:48.239Z","_id":"3b7f1b014a2c4461ad84fec25a45c7c6"},{"name":"Worldpay Group Plc","price":"256.50","change_amount":"-2.20","change_percent":"-0.85%","date":"2016-12-07T16:47:15.485Z","_id":"2c1db07882a24bec820aaa778aaac6ec"},{"name":"Worldpay Group Plc","price":"256.50","change_amount":"-2.20","change_percent":"-0.85%","date":"2016-12-07T16:48:02.006Z","_id":"57c97159ed7b438591cca2f09497fada"},{"name":"Worldpay Group Plc","price":"256.50","change_amount":"-2.20","change_percent":"-0.85%","date":"2016-12-07T16:48:08.118Z","_id":"bcae56be6667460ca3b87257abad4f57"},{"name":"Worldpay Group Plc","price":"256.50","change_amount":"-2.20","change_percent":"-0.85%","date":"2016-12-07T16:50:06.906Z","_id":"f7c5043a7b6a4b8ca8961a9df5a79a22"},{"name":"Worldpay Group Plc","price":"256.60","change_amount":"-2.20","change_percent":"-0.85%","date":"2016-12-07T16:54:56.156Z","_id":"1268c401dd3142dfa5b2f4b9d14b155a"},{"name":"Worldpay Group Plc","price":"256.60","change_amount":"-2.20","change_percent":"-0.85%","date":"2016-12-07T16:57:09.405Z","_id":"0089d096b919419f9bbd0d78c2a7cc5f"},{"name":"Worldpay Group Plc","price":"256.60","change_amount":"-2.20","change_percent":"-0.85%","date":"2016-12-07T17:00:45.873Z","_id":"e33625e3a287498fa201c3158dc6e855"},{"name":"Worldpay Group Plc","price":"256.60","change_amount":"-2.20","change_percent":"-0.85%","date":"2016-12-07T17:02:27.028Z","_id":"4d9c4e5560f14a6a8c809787645220a6"},{"name":"Worldpay Group Plc","price":"256.60","change_amount":"-2.20","change_percent":"-0.85%","date":"2016-12-07T17:05:05.166Z","_id":"e703d0a486594550aec651cae68fd3f6"},{"name":"Worldpay Group Plc","price":"256.60","change_amount":"-2.20","change_percent":"-0.85%","date":"2016-12-07T17:09:04.610Z","_id":"d35bcd76da134a6fbf8700df7d8e9cfd"},{"name":"Worldpay Group Plc","price":"256.60","change_amount":"-2.20","change_percent":"-0.85%","date":"2016-12-07T17:09:20.349Z","_id":"eccfce2df5c6442b9e13c557ea4f7d6e"},{"name":"Worldpay Group Plc","price":"256.60","change_amount":"-2.20","change_percent":"-0.85%","date":"2016-12-07T17:09:40.249Z","_id":"940c7ecae30a479faa45c443b87da2af"},{"name":"Worldpay Group Plc","price":"256.60","change_amount":"-2.20","change_percent":"-0.85%","date":"2016-12-07T17:09:57.331Z","_id":"5b961bfb4586431cbe72aad8d84f9f7e"},{"name":"Worldpay Group Plc","price":"256.60","change_amount":"-2.20","change_percent":"-0.85%","date":"2016-12-07T17:10:31.700Z","_id":"585cd75906f349ca8fc2fcba3a01beb3"},{"name":"Worldpay Group Plc","price":"256.60","change_amount":"-2.20","change_percent":"-0.85%","date":"2016-12-07T17:11:28.881Z","_id":"45c86062b6ba42baabfcd6809b93da60"},{"name":"Worldpay Group Plc","price":"256.60","change_amount":"-2.20","change_percent":"-0.85%","date":"2016-12-07T17:12:16.127Z","_id":"b433a4175e6b480ba29c60db21484b47"},{"name":"Worldpay Group Plc","price":"256.60","change_amount":"-2.20","change_percent":"-0.85%","date":"2016-12-07T17:12:29.459Z","_id":"5c03c24e2a90478d9858446a52506bc4"},{"name":"Worldpay Group Plc","price":"256.60","change_amount":"-2.20","change_percent":"-0.85%","date":"2016-12-07T17:14:19.262Z","_id":"0e7bea0efd59469eaf49c0220ff4e333"},{"name":"Worldpay Group Plc","price":"256.60","change_amount":"-2.20","change_percent":"-0.85%","date":"2016-12-07T17:16:27.921Z","_id":"7f3fee4c89a34299a99d65e265ee372d"},{"name":"Worldpay Group Plc","price":"256.60","change_amount":"-2.20","change_percent":"-0.85%","date":"2016-12-07T17:23:52.545Z","_id":"7b6265d8bc334d81aec746b237629631"},{"name":"Worldpay Group Plc","price":"256.60","change_amount":"-2.20","change_percent":"-0.85%","date":"2016-12-07T17:25:33.219Z","_id":"0bd643167e8a4b44905f95f467c27b5f"},{"name":"Worldpay Group Plc","price":"256.60","change_amount":"-2.20","change_percent":"-0.85%","date":"2016-12-07T17:26:00.783Z","_id":"25b1a46c6bff4119a88f7bf5ff8f7643"},{"name":"Worldpay Group Plc","price":"256.60","change_amount":"-2.20","change_percent":"-0.85%","date":"2016-12-07T17:26:28.524Z","_id":"bffe214ed0dc4d71bd9565ce0852c6c9"},{"name":"Worldpay Group Plc","price":"256.60","change_amount":"-2.20","change_percent":"-0.85%","date":"2016-12-07T17:26:46.219Z","_id":"c063692f89c24eb2830a7cbb013d431e"},{"name":"Worldpay Group Plc","price":"256.60","change_amount":"-2.20","change_percent":"-0.85%","date":"2016-12-07T17:27:25.347Z","_id":"bb1824b08ed44b59a1db6ca467f2a519"},{"name":"Worldpay Group Plc","price":"256.60","change_amount":"-2.20","change_percent":"-0.85%","date":"2016-12-07T17:27:46.003Z","_id":"17223dd83b4644fe9d1a031287531e77"},{"name":"Worldpay Group Plc","price":"256.60","change_amount":"-2.20","change_percent":"-0.85%","date":"2016-12-07T17:28:05.692Z","_id":"8355f3c4af97468eb09389b8c97bfb1f"},{"name":"Worldpay Group Plc","price":"256.60","change_amount":"-2.20","change_percent":"-0.85%","date":"2016-12-07T17:28:28.839Z","_id":"1709f0a86fd748dd94b501e974b57bab"},{"name":"Worldpay Group Plc","price":"256.60","change_amount":"-2.20","change_percent":"-0.85%","date":"2016-12-07T17:29:11.129Z","_id":"17b6c940a0734dff9c4431b588d2b320"},{"name":"Worldpay Group Plc","price":"256.60","change_amount":"-2.20","change_percent":"-0.85%","date":"2016-12-07T17:30:29.056Z","_id":"5a5ae5752533433291aeaa3014e2a2ee"}]